peak_utility/__init__.py
peak_utility/coordinates/__init__.py
peak_utility/coordinates/manhattan.py
"peak_utility/enumeration/__init__,py"
peak_utility/enumeration/enum_list.py
peak_utility/enumeration/parsing_enum.py
peak_utility/listish/__init__.py
peak_utility/listish/compact.py
peak_utility/names/__init__.py
peak_utility/names/corrections.py
peak_utility/number/__init__.py
peak_utility/number/comparators.py
peak_utility/number/numbertext.py
peak_utility/number/ordinal.py
peak_utility/number/primes.py
peak_utility/number/representational_int.py
peak_utility/number/roman.py
peak_utility/text/__init__.py
peak_utility/text/case.py
peak_utility/text/itemlist.py
peak_utility-0.7.0.dist-info/METADATA
peak_utility-0.7.0.dist-info/WHEEL
peak_utility-0.7.0.dist-info/RECORD
