Metadata-Version: 2.1
Name: peak-utility
Version: 0.7.0
Summary: A library of utilities, created by peaky76
License: GPL-3.0-only
Author: peaky76
Author-email: robertjamespeacock@gmail.com
Requires-Python: >=3.8,<4.0
Classifier: License :: OSI Approved :: GNU General Public License v3 (GPLv3)
Classifier: Programming Language :: Python :: 3
Classifier: Programming Language :: Python :: 3.8
Classifier: Programming Language :: Python :: 3.9
Classifier: Programming Language :: Python :: 3.10
Classifier: Programming Language :: Python :: 3.11
Requires-Dist: deprecation (>=2.1.0,<3.0.0)
Requires-Dist: infix (>=1.2,<2.0)
